CHANGES.rst
MANIFEST.in
README.rst
setup.py
docs/LICENSE.GPL
docs/LICENSE.txt
src/EXTERNALS.txt
src/Products/__init__.py
src/Products.MeetingMons.egg-info/PKG-INFO
src/Products.MeetingMons.egg-info/SOURCES.txt
src/Products.MeetingMons.egg-info/dependency_links.txt
src/Products.MeetingMons.egg-info/namespace_packages.txt
src/Products.MeetingMons.egg-info/not-zip-safe
src/Products.MeetingMons.egg-info/requires.txt
src/Products.MeetingMons.egg-info/top_level.txt
src/Products/MeetingMons/__init__.py
src/Products/MeetingMons/adapters.py
src/Products/MeetingMons/config.py
src/Products/MeetingMons/configure.zcml
src/Products/MeetingMons/interfaces.py
src/Products/MeetingMons/overrides.zcml
src/Products/MeetingMons/profiles.zcml
src/Products/MeetingMons/setuphandlers.py
src/Products/MeetingMons/testing.py
src/Products/MeetingMons/testing.zcml
src/Products/MeetingMons/Extensions/__init__.py
src/Products/MeetingMons/Extensions/plonemeeting_portal_helpers.py
src/Products/MeetingMons/browser/__init__.py
src/Products/MeetingMons/browser/configure.zcml
src/Products/MeetingMons/browser/overrides.py
src/Products/MeetingMons/browser/views.py
src/Products/MeetingMons/locales/PloneMeeting.pot
src/Products/MeetingMons/locales/imio.actionspanel.pot
src/Products/MeetingMons/locales/imio.history.pot
src/Products/MeetingMons/locales/plone.pot
src/Products/MeetingMons/locales/sync_pos.sh
src/Products/MeetingMons/locales/fr/LC_MESSAGES/PloneMeeting.po
src/Products/MeetingMons/locales/fr/LC_MESSAGES/imio.actionspanel.po
src/Products/MeetingMons/locales/fr/LC_MESSAGES/imio.history.po
src/Products/MeetingMons/locales/fr/LC_MESSAGES/plone.po
src/Products/MeetingMons/migrations/__init__.py
src/Products/MeetingMons/migrations/migrate_to_4_1.py
src/Products/MeetingMons/model/MeetingMons.zargo
src/Products/MeetingMons/model/__init__.py
src/Products/MeetingMons/model/generate.conf
src/Products/MeetingMons/model/generate.sh
src/Products/MeetingMons/model/pm_updates.py
src/Products/MeetingMons/profiles/__init__.py
src/Products/MeetingMons/profiles/default/MeetingMons_marker.txt
src/Products/MeetingMons/profiles/default/__init__.py
src/Products/MeetingMons/profiles/default/cssregistry.xml
src/Products/MeetingMons/profiles/default/import_steps.xml
src/Products/MeetingMons/profiles/default/jsregistry.xml
