Metadata-Version: 2.1
Name: Products.MeetingMons
Version: 4.1.2
Summary: Official meetings management for college and council of Mons (PloneMeeting extension profile)
Home-page: http://www.imio.be/produits/gestion-des-deliberations
Author: 
Author-email: 
License: GPL
Platform: UNKNOWN
Classifier: Environment :: Web Environment
Classifier: Framework :: Plone
Classifier: Framework :: Plone :: 4.3
Classifier: Programming Language :: Python
Classifier: Programming Language :: Python :: 2.7
Provides-Extra: templates
Provides-Extra: test
